wfdispatcher/__init__.py
wfdispatcher/_version.py
wfdispatcher/auth/__init__.py
wfdispatcher/auth/auth.py
wfdispatcher/client/__init__.py
wfdispatcher/client/client.py
wfdispatcher/client/standalone.py
wfdispatcher/helpers/__init__.py
wfdispatcher/helpers/extract_access_token_from_req.py
wfdispatcher/helpers/extract_uid_from_req.py
wfdispatcher/helpers/extract_user_from_req.py
wfdispatcher/helpers/generator.py
wfdispatcher/helpers/make_auth_header.py
wfdispatcher/helpers/make_mock_user.py
wfdispatcher/helpers/make_post_body.py
wfdispatcher/helpers/make_user_from_env.py
wfdispatcher/helpers/mockspawner.py
wfdispatcher/helpers/sanitize.py
wfdispatcher/helpers/standalone.py
wfdispatcher/objects/__init__.py
wfdispatcher/objects/workflowmanager.py
wfdispatcher/server/__init__.py
wfdispatcher/server/details.py
wfdispatcher/server/list.py
wfdispatcher/server/logs.py
wfdispatcher/server/new.py
wfdispatcher/server/pods.py
wfdispatcher/server/requirejson.py
wfdispatcher/server/server.py
wfdispatcher/server/singleworkflow.py
wfdispatcher/server/standalone.py
wfdispatcher/server/version.py
wfdispatcher/user/__init__.py
wfdispatcher/user/user.py
wfdispatcher-0.4.2.dist-info/LICENSE
wfdispatcher-0.4.2.dist-info/METADATA
wfdispatcher-0.4.2.dist-info/WHEEL
wfdispatcher-0.4.2.dist-info/entry_points.txt
wfdispatcher-0.4.2.dist-info/top_level.txt
wfdispatcher-0.4.2.dist-info/RECORD
